azuretestcli/__init__.py
azuretestcli/cli.py
azuretestcli/lib/__init__.py
azuretestcli/lib/blobstorage.py
azuretestcli/lib/eventhub.py
azuretestcli/lib/queuestorage.py
azuretestcli/lib/servicebus.py
azuretestcli/lib/tablestorage.py
azure_test_cli-0.4.4.dist-info/LICENSE
azure_test_cli-0.4.4.dist-info/METADATA
azure_test_cli-0.4.4.dist-info/WHEEL
azure_test_cli-0.4.4.dist-info/entry_points.txt
azure_test_cli-0.4.4.dist-info/top_level.txt
azure_test_cli-0.4.4.dist-info/RECORD
