Metadata-Version: 2.1
Name: azure-test-cli
Version: 0.4.4
Summary: CLI to test azure resources, such as servicebus, eventhub, and storage
Home-page: https://github.com/wildengineer/azure-test-cli
Author: Michael Groves
Author-email: mike@wildengineer.com
License: UNKNOWN
Platform: UNKNOWN
Classifier: Programming Language :: Python :: 3
Classifier: License :: OSI Approved :: MIT License
Classifier: Operating System :: OS Independent
Requires-Dist: click
Requires-Dist: asyncio
Requires-Dist: azure-eventhub
Requires-Dist: azure-servicebus
Requires-Dist: azure-storage-blob
